pyshares/__init__.py
pyshares-1.0.dist-info/LICENSE
pyshares-1.0.dist-info/METADATA
pyshares-1.0.dist-info/WHEEL
pyshares-1.0.dist-info/top_level.txt
pyshares-1.0.dist-info/RECORD
