Metadata-Version: 2.1
Name: pyshares
Version: 1.0
Summary: by Wizz1337
Home-page: UNKNOWN
Author: Wizz1337
Author-email: xin1337dev@protonmail.com
License: Eclipse Public License 2.0
Keywords: python,share,tiktok,bot,devcenter
Platform: UNKNOWN
